oows/__init__.py
oows/ecs/__init__.py
oows/ecs/cluster.py
oows/ecs/service.py
oows/ecs/task.py
oows/ecs/task_definition.py
oows-0.0.4.dist-info/METADATA
oows-0.0.4.dist-info/RECORD
oows-0.0.4.dist-info/WHEEL
oows-0.0.4.dist-info/top_level.txt
