Metadata-Version: 2.1
Name: oows
Version: 0.0.4
Summary: An object-oriented friendly & pythonic client for Amazon Web Services (AWS)
Home-page: UNKNOWN
Author: Felipe "Bidu" Rodrigues
Author-email: felipe@felipevr.com
License: LICENSE.md
Platform: UNKNOWN
Classifier: Programming Language :: Python :: 3
Classifier: License :: OSI Approved :: MIT License
Classifier: Operating System :: OS Independent
Requires-Dist: boto3 (==1.7.80)
